[
  {
    "title": "Instrumental variable estimation in semi‐parametric additive hazards models",
    "datasets": [
      "dataset-220"
    ],
    "original": {
      "journal": "Biometrics",
      "valid": "no",
      "notes": "reference matches search_term",
      "search_term": "Illinois Unemployment Insurance",
      "doi": "10.1111/biom.12952"
    }
  },
  {
    "title": "Assessing the effects of reemployment bonuses on job search: A regression discontinuity approach",
    "datasets": [
      "dataset-220"
    ],
    "original": {
      "journal": "Journal of Public Economics",
      "valid": "no ",
      "notes": "reference matches search_term",
      "search_term": "Illinois Unemployment Insurance",
      "doi": "10.1016/j.jpubeco.2018.07.003"
    }
  },
  {
    "title": "Chapter 8 Social Experiments in the Labor Market",
    "datasets": [
      "dataset-220"
    ],
    "original": {
      "journal": "Handbook of Economic Field Experiments",
      "valid": "no",
      "notes": "reference matches search_term",
      "search_term": "Illinois Unemployment Insurance",
      "doi": "10.1016/bs.hefe.2016.10.001"
    }
  },
  {
    "title": "How Major Local Taxes Affect Private Employment",
    "datasets": [
      "dataset-220"
    ],
    "original": {
      "journal": "Economic Development Quarterly",
      "valid": "no",
      "notes": "matched Illinois Unemployment Insurance Act",
      "search_term": "Illinois Unemployment Insurance",
      "doi": "10.1177/0891242412465109"
    }
  },
  {
    "title": "Policies for Displaced Workers: An American Perspective",
    "datasets": [
      "dataset-220"
    ],
    "original": {
      "journal": "SSRN Electronic Journal",
      "valid": "maybe",
      "notes": "paywall",
      "search_term": "Illinois Unemployment Insurance",
      "doi": "10.2139/ssrn.1711192"
    }
  },
  {
    "title": "The Cult of Statistical Significance, How the Standard Error Costs Us Jobs, Justice, and Lives",
    "datasets": [
      "dataset-220"
    ],
    "original": {
      "valid": "no",
      "notes": "book, reference matches search_term",
      "search_term": "Illinois Unemployment Insurance",
      "doi": "10.3998/mpub.186351"
    }
  },
  {
    "title": "Instrumental variables methods in experimental criminological research: what, why and how",
    "datasets": [
      "dataset-220"
    ],
    "original": {
      "journal": "Journal of Experimental Criminology",
      "valid": "no",
      "notes": "reference matches search_term",
      "search_term": "Illinois Unemployment Insurance",
      "doi": "10.1007/s11292-005-5126-x"
    }
  },
  {
    "title": "Investigations in the Workplace",
    "datasets": [
      "dataset-220"
    ],
    "original": {
      "valid": "no",
      "notes": "book",
      "search_term": "Illinois Unemployment Insurance",
      "doi": "10.1201/9780203504796"
    }
  },
  {
    "title": "Why is the standard error of regression so low using historical data? Comments on “size matters”",
    "datasets": [
      "dataset-220"
    ],
    "original": {
      "journal": "The Journal of Socio-Economics",
      "valid": "no",
      "notes": "reference matches search_term",
      "search_term": "Illinois Unemployment Insurance",
      "doi": "10.1016/j.socec.2004.09.029"
    }
  },
  {
    "title": "Significance redux",
    "datasets": [
      "dataset-220"
    ],
    "original": {
      "journal": "The Journal of Socio-Economics",
      "valid": "no",
      "notes": "referenced but not used",
      "search_term": "Illinois Unemployment Insurance",
      "doi": "10.1016/j.socec.2004.09.038"
    }
  },
  {
    "title": "EVALUATING THE EMPLOYMENT IMPACT OF A MANDATORY JOB SEARCH PROGRAM",
    "datasets": [
      "dataset-220"
    ],
    "original": {
      "journal": "Journal of the European Economic Association",
      "valid": "no",
      "notes": "reference matches search_term",
      "search_term": "Illinois Unemployment Insurance",
      "doi": "10.1162/1542476041423368"
    }
  },
  {
    "title": "Sequential testing of duration data: the case of the Pennsylvania ‘reemployment bonus’ experiment",
    "datasets": [
      "dataset-220"
    ],
    "original": {
      "journal": "Journal of Applied Econometrics",
      "valid": "no",
      "notes": "reference matches search_term",
      "search_term": "Illinois Unemployment Insurance",
      "doi": "10.1002/jae.579"
    }
  },
  {
    "title": "Building State and Local Government Analytic Capacity: Using Regional Economic Models for Analysis of Public Policy",
    "datasets": [
      "dataset-220"
    ],
    "original": {
      "journal": "State and Local Government Review",
      "valid": "no",
      "notes": "reference matches search_term",
      "search_term": "Illinois Unemployment Insurance",
      "doi": "10.1177/0160323x9803000302"
    }
  },
  {
    "title": "Introduction",
    "datasets": [
      "dataset-220"
    ],
    "original": {
      "journal": "International Journal of Public Administration",
      "valid": "no",
      "notes": "reference matches search_term",
      "search_term": "Illinois Unemployment Insurance",
      "doi": "10.1080/01900699708525258"
    }
  },
  {
    "title": "Do bonus offers shorten unemployment insurance spells? results from the washington experiment",
    "datasets": [
      "dataset-220"
    ],
    "original": {
      "journal": "Journal of Policy Analysis and Management",
      "valid": "no",
      "notes": "reference matches search_term",
      "search_term": "Illinois Unemployment Insurance",
      "doi": "10.2307/3325152"
    }
  },
  {
    "title": "The Effects of Displacement On Measures of Reemployment Bonus Impacts",
    "datasets": [
      "dataset-220"
    ],
    "original": {
      "journal": "Evaluation Review",
      "valid": "no",
      "notes": "reference matches search_term",
      "search_term": "Illinois Unemployment Insurance",
      "doi": "10.1177/0193841x9301700104"
    }
  },
  {
    "title": "Applying for entitlements: Employers and the targeted jobs tax credit",
    "datasets": [
      "dataset-220"
    ],
    "original": {
      "journal": "Journal of Policy Analysis and Management",
      "valid": "no",
      "notes": "reference matches search_term",
      "search_term": "Illinois Unemployment Insurance",
      "doi": "10.2307/3325511"
    }
  }
]