[
    {
        "authors": [
            "author-f43a3fc020d406fdf990",
            "author-0d0cc4a3b34eef0ca87e"
        ],
        "datasets": [
            "dataset-002"
        ],
        "doi": "10.1177/0042098017740285",
        "journal": "journal-821",
        "pdf": "https://www.economics.uci.edu/research/wp/1718/17-18-04.pdf",
        "title": "Supply-side subsidies to improve food access and dietary outcomes: Evidence from the New Markets Tax Credit",
        "url": "https://www.doi.org/10.1177/0042098017740285"
    },
    {
        "authors": [
            "author-2314d58aa546f1a08379",
            "author-467073b4687879cf7751"
        ],
        "datasets": [
            "dataset-002"
        ],
        "doi": "10.1016/j.ypmed.2016.08.018",
        "journal": "journal-030",
        "title": "The healthfulness of food and beverage purchases after the federal food package revisions: The case of two New England states",
        "url": "https://www.semanticscholar.org/paper/88c8fa09f405ef1ce1297872baee7b0b399fa75d"
    },
    {
        "authors": [
            "author-e13b3ccef1fd5a447a86",
            "author-cbb9831968be600676eb",
            "author-0474e34b1db07f0901bd"
        ],
        "datasets": [
            "dataset-002"
        ],
        "doi": "10.1371/journal.pone.0124351",
        "journal": "journal-001",
        "pdf": "http://europepmc.org/articles/PMC4427330?pdf=render",
        "title": "Relationships between Diet, Alcohol Preference, and Heart Disease and Type 2 Diabetes among Americans",
        "url": "https://www.doi.org/10.1371/journal.pone.0124351"
    },
    {
        "authors": [
            "author-b4052c77f0bc013140c2",
            "author-ab8aa61e37e9671d08bc",
            "author-263c24627cf0117e08d5"
        ],
        "datasets": [
            "dataset-001"
        ],
        "doi": "10.1080/10454446.2018.1428259",
        "journal": "journal-004",
        "title": "A comparative analysis of hedonic models of nutrition information and health claims on food products: An application to soup products",
        "url": "https://www.doi.org/10.1080/10454446.2018.1428259"
    },
    {
        "authors": [
            "author-6d9a3cee5ea79ff0d434",
            "author-0fc06006c7552e9e30d6",
            "author-80cce905bb3f25881985",
            "author-8e7e0b1b09c9f2b52716"
        ],
        "datasets": [
            "dataset-001"
        ],
        "doi": "10.1007/s10603-018-9396-x",
        "journal": "journal-005",
        "title": "Evidence from Retail Food Markets That Consumers Are Confused by Natural and Organic Food Labels",
        "url": "https://doi.org/10.1007/s10603-018-9396-x"
    },
    {
        "authors": [
            "author-577bd58f3fe6e57f9488",
            "author-8a63221dd5f8b7b47a6e",
            "author-b63f8b096f7aba37c2cf"
        ],
        "datasets": [
            "dataset-002"
        ],
        "doi": "10.1080/15140326.2018.1526869",
        "journal": "journal-006",
        "pdf": "https://www.tandfonline.com/doi/pdf/10.1080/15140326.2018.1526869?needAccess=true",
        "title": "A new approach to estimate household food demand with panel data",
        "url": "https://doi.org/10.1080/15140326.2018.1526869"
    },
    {
        "authors": [
            "author-6f901ec75d4cf9daf548",
            "author-e698a9515bc11d22a05e",
            "author-c234730f5292a22f8af2"
        ],
        "datasets": [
            "dataset-001"
        ],
        "doi": "10.3168/jds.2015-10410",
        "journal": "journal-007",
        "pdf": "http://www.journalofdairyscience.org/article/S0022030216301369/pdf",
        "title": "The effects of retail concentration on retail dairy product prices in the United States",
        "url": "https://doi.org/10.3168/jds.2015-10410"
    },
    {
        "authors": [
            "author-f4aed4d78242c46b91fc",
            "author-0015e3f1366ddd97f21a",
            "author-0b131d2aad0d75fff72e",
            "author-352b42365c020d03ab8e",
            "author-1c534705e583c45b9ba2"
        ],
        "datasets": [
            "dataset-002"
        ],
        "doi": "10.1016/j.jand.2017.01.011",
        "journal": "journal-008",
        "title": "No Fat, No Sugar, No Salt . . . No Problem? Prevalence of \"Low-Content\" Nutrient Claims and Their Associations with the Nutritional Profile of Food and Beverage Purchases in the United States",
        "url": "https://doi.org/10.1016/j.jand.2017.01.011"
    },
    {
        "authors": [
            "author-6d9a3cee5ea79ff0d434",
            "author-501979a275697b40b2d7"
        ],
        "datasets": [
            "dataset-001"
        ],
        "doi": "10.1093/erae/jbv032",
        "journal": "journal-009",
        "pdf": "https://academic.oup.com/erae/article-pdf/43/4/585/9601072/jbv032.pdf",
        "title": "Consumers' welfare and off-season produce imports",
        "url": "https://doi.org/10.1093/erae/jbv032"
    },
    {
        "authors": [
            "author-6f901ec75d4cf9daf548",
            "author-d3c2196a94e60ac10a5e",
            "author-e698a9515bc11d22a05e",
            "author-c234730f5292a22f8af2"
        ],
        "datasets": [
            "dataset-001"
        ],
        "doi": "10.1093/erae/jby026",
        "journal": "journal-009",
        "pdf": "https://doi.org/10.1093/erae/jby026",
        "title": "The relationship between price and retail concentration: evidence from the US food industry",
        "url": "https://www.semanticscholar.org/paper/2c0ceda099610430b9c0d4b4c41a1df391510bf0"
    },
    {
        "authors": [
            "author-f23dd23fbbdfdb5bddf2",
            "author-6f1da7407e0d68a3516d"
        ],
        "datasets": [
            "dataset-001"
        ],
        "doi": "10.1093/aepp/ppy018",
        "journal": "journal-010",
        "pdf": "https://doi.org/10.1093/aepp/ppy018",
        "title": "Documenting the Link Between Poor Food Access and Less Healthy Product Assortment Across the U.S",
        "url": "https://www.doi.org/10.1093/aepp/ppy018"
    },
    {
        "authors": [
            "author-bb85cb26bc5eb4355b07",
            "author-39745706c9a08845de07",
            "author-c730e484d2130e43df7b",
            "author-0b5f2ad9f782e1a58087",
            "author-d175f03b9c3ab93d4eea",
            "author-a080408fcbb21d286b63"
        ],
        "datasets": [
            "dataset-001"
        ],
        "doi": "10.1093/ajae/aay002",
        "journal": "journal-011",
        "title": "Spatial and Temporal Variation in the Value of the Women, Infants, and Children Program's Fruit and Vegetable Voucher",
        "url": "https://www.semanticscholar.org/paper/cfc88a1b0be0db09c90cc18ce8b06a7bf955900b"
    },
    {
        "authors": [
            "author-8f238854e820dde1546e",
            "author-59ae4422640ad582c396",
            "author-f060b8d92bbb99191c22"
        ],
        "datasets": [
            "dataset-002"
        ],
        "doi": "10.1177/0890117117740935",
        "journal": "journal-012",
        "title": "Chronic Disease, Prescription Medications, and Food Purchases",
        "url": "https://www.semanticscholar.org/paper/7227e869eed73c8e64b176b19d711161feffc279"
    },
    {
        "authors": [
            "author-f93ee3043bf19cf2d4dc",
            "author-6f1da7407e0d68a3516d",
            "author-cbb9831968be600676eb"
        ],
        "datasets": [
            "dataset-002"
        ],
        "doi": "10.1177/0890117118786871",
        "journal": "journal-012",
        "pdf": "https://journals.sagepub.com/doi/pdf/10.1177/0890117118786871",
        "title": "The Healthfulness of Food-at-Home Expenditures, the Local Food Environment, and Childhood Obesity",
        "url": "https://doi.org/10.1177/0890117118786871"
    },
    {
        "authors": [
            "author-09ca1a12ed7f2dbe8b10",
            "author-8a63221dd5f8b7b47a6e",
            "author-4ad2442a7f2a13e75fff",
            "author-fdbff674878174e15e9b"
        ],
        "datasets": [
            "dataset-002"
        ],
        "doi": "10.1111/agec.12222",
        "journal": "journal-013",
        "pdf": "http://hdl.handle.net/10.1111/agec.12222",
        "title": "Modeling price transmission between farm and retail prices: a soft switches approach",
        "url": "https://doi.org/10.1111/agec.12222"
    },
    {
        "authors": [
            "author-577bd58f3fe6e57f9488",
            "author-fdbff674878174e15e9b",
            "author-8a63221dd5f8b7b47a6e"
        ],
        "datasets": [
            "dataset-002"
        ],
        "doi": "10.1111/agec.12143",
        "journal": "journal-013",
        "title": "The quantity and variety of households' meat purchases: A censored demand system approach",
        "url": "https://www.semanticscholar.org/paper/0a783ea907749c158a2ad1ba4ef36b22ac84e256"
    }
]